yamodel/modelobj.py
yamodel/yamodel.py
yamodel/__init__.py
yamodel-0.0.1.dist-info/DESCRIPTION.rst
yamodel-0.0.1.dist-info/METADATA
yamodel-0.0.1.dist-info/metadata.json
yamodel-0.0.1.dist-info/RECORD
yamodel-0.0.1.dist-info/top_level.txt
yamodel-0.0.1.dist-info/WHEEL
