Metadata-Version: 2.0
Name: yamodel
Version: 0.0.1
Summary: A simple way of performing unified domain modeling using YAML documents.
Home-page: http://pypi.python.org/pypi/yamodel/
Author: Kyle Patrick
Author-email: UNKNOWN
License: UNKNOWN
Platform: UNKNOWN
Requires-Dist: PyYAML
